SoyleApp/__init__.py
SoyleApp/client.py
SoyleApp/constants.py
SoyleApp/exceptions.py
SoyleApp-1.1.0.dist-info/LICENSE
SoyleApp-1.1.0.dist-info/METADATA
SoyleApp-1.1.0.dist-info/WHEEL
SoyleApp-1.1.0.dist-info/top_level.txt
SoyleApp-1.1.0.dist-info/RECORD
