Metadata-Version: 2.2
Name: SoyleApp
Version: 1.1.0
Summary: A Python library for interacting with the Soyle Translation API.
Home-page: https://github.com/Dari4ok/SoyleApp
Author: Dari4ok
Author-email: Dari4ok.vsl@gmail.com
License: MIT
Classifier: Programming Language :: Python :: 3
Classifier: License :: OSI Approved :: MIT License
Classifier: Operating System :: OS Independent
Requires-Python: >=3.6
License-File: LICENSE
Requires-Dist: requests
Dynamic: author
Dynamic: author-email
Dynamic: classifier
Dynamic: description
Dynamic: description-content-type
Dynamic: home-page
Dynamic: license
Dynamic: requires-dist
Dynamic: requires-python
Dynamic: summary
